Metadata-Version: 2.1
Name: scrapy-db-pipeline
Version: 1.0
Summary: persist item to the database table
Home-page: https://github.com/feng409/scrapy_db_pipeline
Author: chemf
Author-email: eoyohe@gmail.com
License: MIT License
Keywords: scrapy pipeline
Platform: UNKNOWN
Classifier: Framework :: Scrapy
Classifier: Programming Language :: Python
Classifier: License :: OSI Approved :: MIT License
